{
    "data": {
        "averageScore": 5.0,
        "badCount": 700,
        "badRate": "0.01",
        "comments": [
            {
                "canReply": "0",
                "commentId": 81536602980333,
                "commentLevel": "好评",
                "content": "非常不错，手感也很好",
                "creationTime": "2019-09-30 17:03:23+0800",
                "gradeCode": 2,
                "headImage": "https://res.vmallres.com/rms/comment/image/U0306/ad03d3a6ce804da13d784b022f148306/7064f168a63c32c36b3672b9.jpg",
                "headImageDb": "",
                "images": [],
                "isAnonymous": 1,
                "isShow": 1,
                "isTop": 0,
                "likes": 0,
                "productId": 10086102942203,
                "replies": [
                    {
                        "headImage": "https://res.vmallres.com/nwap/20170828/images/echannelWap/misc/defaultface_customer_service.png",
                        "headImageDb": "",
                        "likes": 0,
                        "parentId": 0,
                        "replyContent": "亲爱哒，您对宝贝的肯定，是快乐时钟，在生活里摇摆；是幸福种子，在人生里发芽；是美好阳光，在生命里灿烂。祝您天天开心，幸福永远~",
                        "replyId": 81543469239461,
                        "replyTime": "2019-09-30 18:57:49+0800",
                        "replyerName": "华为商城客服",
                        "type": 0
                    }
                ],
                "replyCount": 1,
                "score": 5,
                "showImageCount": 0,
                "skuAttrs": "天空之境,全网通 8GB+128GB,官方标配",
                "skuCode": "2601010102603",
                "skuName": "HUAWEI P30 Pro 麒麟980 超感光徕卡四摄 屏内指纹 双景录像 8GB+128GB 全网通版（天空之境）",
                "tags": [],
                "title": "",
                "type": 0,
                "userName": "Z*****"
            },
            {
                "canReply": "0",
                "commentId": 81534990102408,
                "commentLevel": "好评",
                "content": "第二次从华为商城买手机，售后很好下次还会从华为商城买华为的产品。上次买的麦芒6这次买p30PrO，给华为商城10分好评",
                "creationTime": "2019-09-30 16:36:30+0800",
                "gradeCode": 3,
                "headImage": "https://res.vmallres.com/nwap/20170828/images/echannelWap/misc/defaultface_user_after.png",
                "headImageDb": "",
                "images": [
                    {
                        "id": 81534990102409,
                        "large": "https://res.vmallres.com/rms/comment/image/U0132/8b9a5db276fa5b8ebeafc34a5356e628/1080/80dfb26fae17c77fad08469f.jpg",
                        "small": "https://res.vmallres.com/rms/comment/image/U0132/8b9a5db276fa5b8ebeafc34a5356e628/100/80dfb26fae17c77fad08469f.jpg"
                    },
                    {
                        "id": 81534990102410,
                        "large": "https://res.vmallres.com/rms/comment/image/U0132/8b9a5db276fa5b8ebeafc34a5356e628/1080/cec2fe7294ee25516746d0ab.jpg",
                        "small": "https://res.vmallres.com/rms/comment/image/U0132/8b9a5db276fa5b8ebeafc34a5356e628/100/cec2fe7294ee25516746d0ab.jpg"
                    },
                    {
                        "id": 81534990102411,
                        "large": "https://res.vmallres.com/rms/comment/image/U0132/8b9a5db276fa5b8ebeafc34a5356e628/1080/28bf00f1e5bf23ee47ea4f3d.jpg",
                        "small": "https://res.vmallres.com/rms/comment/image/U0132/8b9a5db276fa5b8ebeafc34a5356e628/100/28bf00f1e5bf23ee47ea4f3d.jpg"
                    }
                ],
                "isAnonymous": 1,
                "isShow": 1,
                "isTop": 4,
                "likes": 0,
                "productId": 10086102942203,
                "replies": [],
                "replyCount": 0,
                "score": 5,
                "showImageCount": 0,
                "skuAttrs": "天空之境,全网通 8GB+128GB,官方标配",
                "skuCode": "2601010102603",
                "skuName": "HUAWEI P30 Pro 麒麟980 超感光徕卡四摄 屏内指纹 双景录像 8GB+128GB 全网通版（天空之境）",
                "tags": [],
                "title": "",
                "type": 0,
                "userName": "无***"
            },
            {
                "canReply": "0",
                "commentId": 81534672267070,
                "commentLevel": "好评",
                "content": "手机很好，就是在物流方面体验很不好，从成都到重庆用了4天，是在古代吗？送快递要这么久",
                "creationTime": "2019-09-30 16:31:12+0800",
                "gradeCode": 3,
                "headImage": "https://res.vmallres.com/rms/comment/image/U0136/6022d217492976e313d102ed.jpg",
                "headImageDb": "",
                "images": [
                    {
                        "id": 81534672267071,
                        "large": "https://res.vmallres.com/rms/comment/image/U0136/910a61658664e2dfcb1311d0569a3f9d/1080/4ddac023602cf95533f09666.jpg",
                        "small": "https://res.vmallres.com/rms/comment/image/U0136/910a61658664e2dfcb1311d0569a3f9d/100/4ddac023602cf95533f09666.jpg"
                    },
                    {
                        "id": 81534672267073,
                        "large": "https://res.vmallres.com/rms/comment/image/U0136/910a61658664e2dfcb1311d0569a3f9d/1080/ed4e36e71bd20ca6b37cbb61.jpg",
                        "small": "https://res.vmallres.com/rms/comment/image/U0136/910a61658664e2dfcb1311d0569a3f9d/100/ed4e36e71bd20ca6b37cbb61.jpg"
                    }
                ],
                "isAnonymous": 1,
                "isShow": 1,
                "isTop": 4,
                "likes": 0,
                "productId": 10086102942203,
                "replies": [],
                "replyCount": 0,
                "score": 5,
                "showImageCount": 0,
                "skuAttrs": "天空之境,全网通 8GB+256GB,官方标配",
                "skuCode": "2601010102608",
                "skuName": "HUAWEI P30 Pro 麒麟980 超感光徕卡四摄 屏内指纹 双景录像 8GB+256GB 全网通版（天空之境）",
                "tags": [],
                "title": "",
                "type": 0,
                "userName": "V*"
            },
            {
                "canReply": "0",
                "commentId": 81534550427708,
                "commentLevel": "好评",
                "content": "手机很好看，拍照很好，就是临近国庆，快递在东莞呆了一天一夜，等的着急",
                "creationTime": "2019-09-30 16:29:10+0800",
                "gradeCode": 1,
                "headImage": "https://res.vmallres.com/nwap/20170828/images/echannelWap/misc/defaultface_user_after.png",
                "headImageDb": "",
                "images": [
                    {
                        "id": 81534550428709,
                        "large": "https://res.vmallres.com/rms/comment/image/U0156/ddcb27920ccb4a0220874648d305166c/1080/a005f12aa113ad98adede612.jpg",
                        "small": "https://res.vmallres.com/rms/comment/image/U0156/ddcb27920ccb4a0220874648d305166c/100/a005f12aa113ad98adede612.jpg"
                    }
                ],
                "isAnonymous": 1,
                "isShow": 1,
                "isTop": 4,
                "likes": 0,
                "productId": 10086102942203,
                "replies": [],
                "replyCount": 0,
                "score": 5,
                "showImageCount": 0,
                "skuAttrs": "珠光贝母,全网通 8GB+512GB,官方标配",
                "skuCode": "2601010102615",
                "skuName": "HUAWEI P30 Pro 麒麟980 超感光徕卡四摄 屏内指纹 曲面屏 双景录像 8GB+512GB 全网通版（珠光贝母）",
                "tags": [],
                "title": "",
                "type": 0,
                "userName": "155****0521"
            },
            {
                "canReply": "0",
                "commentId": 81533798655018,
                "commentLevel": "好评",
                "content": "很喜欢",
                "creationTime": "2019-09-30 16:16:39+0800",
                "gradeCode": 3,
                "headImage": "https://res.vmallres.com/nwap/20170828/images/echannelWap/misc/defaultface_user_after.png",
                "headImageDb": "",
                "images": [],
                "isAnonymous": 1,
                "isShow": 1,
                "isTop": 0,
                "likes": 0,
                "productId": 10086102942203,
                "replies": [],
                "replyCount": 0,
                "score": 5,
                "showImageCount": 0,
                "skuAttrs": "亮黑色,全网通 8GB+256GB,官方标配",
                "skuCode": "2601010102606",
                "skuName": "HUAWEI P30 Pro 麒麟980 超感光徕卡四摄 屏内指纹 双景录像 8GB+256GB 全网通版（亮黑色）",
                "tags": [],
                "title": "",
                "type": 0,
                "userName": "七*"
            },
            {
                "canReply": "0",
                "commentId": 81533474635729,
                "commentLevel": "好评",
                "content": "用户未填写评价内容",
                "creationTime": "2019-09-30 16:11:15+0800",
                "gradeCode": 5,
                "headImage": "https://res.vmallres.com/rms/comment/image/U0507/7a609819e6c80ca349d578ba.jpg",
                "headImageDb": "",
                "images": [],
                "isAnonymous": 1,
                "isShow": 1,
                "isTop": 0,
                "likes": 0,
                "productId": 10086102942203,
                "replies": [],
                "replyCount": 0,
                "score": 5,
                "showImageCount": 0,
                "skuAttrs": "天空之境,全网通 8GB+256GB,官方标配",
                "skuCode": "2601010102608",
                "skuName": "HUAWEI P30 Pro 麒麟980 超感光徕卡四摄 屏内指纹 双景录像 8GB+256GB 全网通版（天空之境）",
                "tags": [],
                "title": "",
                "type": 0,
                "userName": "c*"
            },
            {
                "canReply": "0",
                "commentId": 81533474612986,
                "commentLevel": "好评",
                "content": "用户未填写评价内容",
                "creationTime": "2019-09-30 16:11:15+0800",
                "gradeCode": 5,
                "headImage": "https://res.vmallres.com/rms/comment/image/U0507/7a609819e6c80ca349d578ba.jpg",
                "headImageDb": "",
                "images": [],
                "isAnonymous": 1,
                "isShow": 1,
                "isTop": 0,
                "likes": 0,
                "productId": 10086102942203,
                "replies": [],
                "replyCount": 0,
                "score": 5,
                "showImageCount": 0,
                "skuAttrs": "极光色,全网通 8GB+256GB,官方标配",
                "skuCode": "2601010102607",
                "skuName": "HUAWEI P30 Pro 麒麟980 超感光徕卡四摄 屏内指纹 双景录像 8GB+256GB 全网通版（极光色）",
                "tags": [],
                "title": "",
                "type": 0,
                "userName": "c*"
            },
            {
                "canReply": "0",
                "commentId": 81533474522217,
                "commentLevel": "好评",
                "content": "用户未填写评价内容",
                "creationTime": "2019-09-30 16:11:15+0800",
                "gradeCode": 5,
                "headImage": "https://res.vmallres.com/rms/comment/image/U0507/7a609819e6c80ca349d578ba.jpg",
                "headImageDb": "",
                "images": [],
                "isAnonymous": 1,
                "isShow": 1,
                "isTop": 0,
                "likes": 0,
                "productId": 10086102942203,
                "replies": [],
                "replyCount": 0,
                "score": 5,
                "showImageCount": 0,
                "skuAttrs": "亮黑色,全网通 8GB+256GB,官方标配",
                "skuCode": "2601010102606",
                "skuName": "HUAWEI P30 Pro 麒麟980 超感光徕卡四摄 屏内指纹 双景录像 8GB+256GB 全网通版（亮黑色）",
                "tags": [],
                "title": "",
                "type": 0,
                "userName": "c*"
            },
            {
                "canReply": "0",
                "commentId": 81533410796169,
                "commentLevel": "好评",
                "content": "话不多说，又给女朋友买了一部",
                "creationTime": "2019-09-30 16:10:11+0800",
                "gradeCode": 2,
                "headImage": "https://res.vmallres.com/nwap/20170828/images/echannelWap/misc/defaultface_user_after.png",
                "headImageDb": "",
                "images": [
                    {
                        "id": 81533410796170,
                        "large": "https://res.vmallres.com/rms/comment/image/U0026/970952f93554dc25405cfdccf4d08ed2/1080/f8d03b29391bfbef1c362146.jpg",
                        "small": "https://res.vmallres.com/rms/comment/image/U0026/970952f93554dc25405cfdccf4d08ed2/100/f8d03b29391bfbef1c362146.jpg"
                    }
                ],
                "isAnonymous": 1,
                "isShow": 1,
                "isTop": 0,
                "likes": 0,
                "productId": 10086102942203,
                "replies": [],
                "replyCount": 0,
                "score": 5,
                "showImageCount": 0,
                "skuAttrs": "极光色,全网通 8GB+128GB,官方标配",
                "skuCode": "2601010102602",
                "skuName": "HUAWEI P30 Pro 麒麟980 超感光徕卡四摄 屏内指纹 双景录像 8GB+128GB 全网通版（极光色）",
                "tags": [],
                "title": "",
                "type": 0,
                "userName": "158****0745"
            },
            {
                "canReply": "0",
                "commentId": 81532716489116,
                "commentLevel": "好评",
                "content": "感觉很不错，屏幕很大，很流畅",
                "creationTime": "2019-09-30 15:58:36+0800",
                "gradeCode": 0,
                "headImage": "https://res.vmallres.com/rms/comment/image/U0280/af3ef7de69dd84c6e8fb948a0a7c9800/7e0293a6212ebfacb87e7a14.jpg",
                "headImageDb": "",
                "images": [],
                "isAnonymous": 1,
                "isShow": 1,
                "isTop": 0,
                "likes": 0,
                "productId": 10086102942203,
                "replies": [],
                "replyCount": 0,
                "score": 5,
                "showImageCount": 0,
                "skuAttrs": "天空之境,全网通 8GB+128GB,官方标配",
                "skuCode": "2601010102603",
                "skuName": "HUAWEI P30 Pro 麒麟980 超感光徕卡四摄 屏内指纹 双景录像 8GB+128GB 全网通版（天空之境）",
                "tags": [],
                "title": "",
                "type": 0,
                "userName": "l*****"
            },
            {
                "canReply": "0",
                "commentId": 81532697557958,
                "commentLevel": "好评",
                "content": "好看，好用，人性化",
                "creationTime": "2019-09-30 15:58:18+0800",
                "gradeCode": 2,
                "headImage": "https://res.vmallres.com/nwap/20170828/images/echannelWap/misc/defaultface_user_after.png",
                "headImageDb": "",
                "images": [],
                "isAnonymous": 1,
                "isShow": 1,
                "isTop": 0,
                "likes": 0,
                "productId": 10086102942203,
                "replies": [],
                "replyCount": 0,
                "score": 5,
                "showImageCount": 0,
                "skuAttrs": "天空之境,全网通 8GB+128GB,官方标配",
                "skuCode": "2601010102603",
                "skuName": "HUAWEI P30 Pro 麒麟980 超感光徕卡四摄 屏内指纹 双景录像 8GB+128GB 全网通版（天空之境）",
                "tags": [],
                "title": "",
                "type": 0,
                "userName": "k***********"
            },
            {
                "canReply": "0",
                "commentId": 81532578458206,
                "commentLevel": "好评",
                "content": "手机非常好用，手感超好！我一直都在用华为手机，这款华为手机真不错！超喜欢！",
                "creationTime": "2019-09-30 15:56:18+0800",
                "gradeCode": 3,
                "headImage": "https://res.vmallres.com/nwap/20170828/images/echannelWap/misc/defaultface_user_after.png",
                "headImageDb": "",
                "images": [],
                "isAnonymous": 1,
                "isShow": 1,
                "isTop": 2,
                "likes": 0,
                "productId": 10086102942203,
                "replies": [
                    {
                        "headImage": "https://res.vmallres.com/nwap/20170828/images/echannelWap/misc/defaultface_customer_service.png",
                        "headImageDb": "",
                        "likes": 0,
                        "parentId": 0,
                        "replyContent": "亲爱哒，您对宝贝的肯定，是快乐时钟，在生活里摇摆；是幸福种子，在人生里发芽；是美好阳光，在生命里灿烂。祝您天天开心，幸福永远~",
                        "replyId": 81543495574464,
                        "replyTime": "2019-09-30 18:58:16+0800",
                        "replyerName": "华为商城客服",
                        "type": 0
                    }
                ],
                "replyCount": 1,
                "score": 5,
                "showImageCount": 0,
                "skuAttrs": "极光色,全网通 8GB+128GB,官方标配",
                "skuCode": "2601010102602",
                "skuName": "HUAWEI P30 Pro 麒麟980 超感光徕卡四摄 屏内指纹 双景录像 8GB+128GB 全网通版（极光色）",
                "tags": [],
                "title": "",
                "type": 0,
                "userName": "132****2959"
            },
            {
                "canReply": "0",
                "commentId": 81531564896109,
                "commentLevel": "好评",
                "content": "很不错的一部手机，这个价位打游戏再卡那就不用再用手机啦，送的小音箱也不错，音质很棒！",
                "creationTime": "2019-09-30 15:39:25+0800",
                "gradeCode": 3,
                "headImage": "https://res.vmallres.com/rms/comment/image/U0033/e6b8991e737b9186190c08ac.jpg",
                "headImageDb": "",
                "images": [],
                "isAnonymous": 1,
                "isShow": 1,
                "isTop": 2,
                "likes": 0,
                "productId": 10086102942203,
                "replies": [],
                "replyCount": 0,
                "score": 5,
                "showImageCount": 0,
                "skuAttrs": "极光色,全网通 8GB+128GB,官方标配",
                "skuCode": "2601010102602",
                "skuName": "HUAWEI P30 Pro 麒麟980 超感光徕卡四摄 屏内指纹 双景录像 8GB+128GB 全网通版（极光色）",
                "tags": [],
                "title": "",
                "type": 0,
                "userName": "默****"
            },
            {
                "canReply": "0",
                "commentId": 81531300976099,
                "commentLevel": "好评",
                "content": "棒极了",
                "creationTime": "2019-09-30 15:35:01+0800",
                "gradeCode": 0,
                "headImage": "https://res.vmallres.com/nwap/20170828/images/echannelWap/misc/defaultface_user_after.png",
                "headImageDb": "",
                "images": [],
                "isAnonymous": 1,
                "isShow": 1,
                "isTop": 0,
                "likes": 0,
                "productId": 10086102942203,
                "replies": [],
                "replyCount": 0,
                "score": 5,
                "showImageCount": 0,
                "skuAttrs": "天空之境,全网通 8GB+512GB,官方标配",
                "skuCode": "2601010102613",
                "skuName": "HUAWEI P30 Pro 麒麟980 超感光徕卡四摄 屏内指纹 曲面屏 双景录像 8GB+512GB 全网通版（天空之境）",
                "tags": [],
                "title": "",
                "type": 0,
                "userName": "*"
            },
            {
                "canReply": "0",
                "commentId": 81530859869250,
                "commentLevel": "好评",
                "content": "用户未填写评价内容",
                "creationTime": "2019-09-30 15:27:40+0800",
                "gradeCode": 0,
                "headImage": "https://res.vmallres.com/rms/comment/image/U0141/bccb8a70e44aed7340aea07f5241bdc5/66f0d2d95f6cc4010f3d0b78.jpg",
                "headImageDb": "",
                "images": [
                    {
                        "id": 81530860253251,
                        "large": "https://res.vmallres.com/rms/comment/image/U0141/bccb8a70e44aed7340aea07f5241bdc5/1080/8a91add072f975cd05b8e4b6.jpg",
                        "small": "https://res.vmallres.com/rms/comment/image/U0141/bccb8a70e44aed7340aea07f5241bdc5/100/8a91add072f975cd05b8e4b6.jpg"
                    },
                    {
                        "id": 81530860253252,
                        "large": "https://res.vmallres.com/rms/comment/image/U0141/bccb8a70e44aed7340aea07f5241bdc5/1080/1c5d4179fa1b022594845cd8.jpg",
                        "small": "https://res.vmallres.com/rms/comment/image/U0141/bccb8a70e44aed7340aea07f5241bdc5/100/1c5d4179fa1b022594845cd8.jpg"
                    }
                ],
                "isAnonymous": 1,
                "isShow": 1,
                "isTop": 0,
                "likes": 0,
                "productId": 10086102942203,
                "replies": [],
                "replyCount": 0,
                "score": 5,
                "showImageCount": 0,
                "skuAttrs": "天空之境,全网通 8GB+128GB,官方标配",
                "skuCode": "2601010102603",
                "skuName": "HUAWEI P30 Pro 麒麟980 超感光徕卡四摄 屏内指纹 双景录像 8GB+128GB 全网通版（天空之境）",
                "tags": [],
                "title": "",
                "type": 0,
                "userName": "蒙*"
            },
            {
                "canReply": "0",
                "commentId": 81530535561030,
                "commentLevel": "好评",
                "content": "非常不错，反应速度快，拍照功能强大",
                "creationTime": "2019-09-30 15:22:16+0800",
                "gradeCode": 3,
                "headImage": "https://res.vmallres.com/nwap/20170828/images/echannelWap/misc/defaultface_user_after.png",
                "headImageDb": "",
                "images": [
                    {
                        "id": 81530535561031,
                        "large": "https://res.vmallres.com/rms/comment/image/U0752/5dc8f71046750f017c3c03ea4571a05c/1080/7724e2a9322b6b47c72e9057.jpg",
                        "small": "https://res.vmallres.com/rms/comment/image/U0752/5dc8f71046750f017c3c03ea4571a05c/100/7724e2a9322b6b47c72e9057.jpg"
                    }
                ],
                "isAnonymous": 1,
                "isShow": 1,
                "isTop": 0,
                "likes": 0,
                "productId": 10086102942203,
                "replies": [],
                "replyCount": 0,
                "score": 5,
                "showImageCount": 0,
                "skuAttrs": "赤茶橘,全网通 8GB+256GB,官方标配",
                "skuCode": "2601010102609",
                "skuName": "HUAWEI P30 Pro 麒麟980 超感光徕卡四摄 屏内指纹 双景录像 8GB+256GB 全网通版（赤茶橘）",
                "tags": [],
                "title": "",
                "type": 0,
                "userName": "包*"
            },
            {
                "canReply": "0",
                "commentId": 81530285445850,
                "commentLevel": "好评",
                "content": "很漂亮，老婆大人很满意！",
                "creationTime": "2019-09-30 15:18:05+0800",
                "gradeCode": 3,
                "headImage": "https://res.vmallres.com/rms/comment/image/U0856/da3b1125a02501c6d9d0dde21e075233/7a8db3e0eb0e42e397478b8b.jpg",
                "headImageDb": "",
                "images": [
                    {
                        "id": 81530285445851,
                        "large": "https://res.vmallres.com/rms/comment/image/U0856/da3b1125a02501c6d9d0dde21e075233/1080/85e7310741d47446abfed8f2.jpg",
                        "small": "https://res.vmallres.com/rms/comment/image/U0856/da3b1125a02501c6d9d0dde21e075233/100/85e7310741d47446abfed8f2.jpg"
                    },
                    {
                        "id": 81530285445852,
                        "large": "https://res.vmallres.com/rms/comment/image/U0856/da3b1125a02501c6d9d0dde21e075233/1080/72392052d7a1c5daa6cd6491.jpg",
                        "small": "https://res.vmallres.com/rms/comment/image/U0856/da3b1125a02501c6d9d0dde21e075233/100/72392052d7a1c5daa6cd6491.jpg"
                    }
                ],
                "isAnonymous": 1,
                "isShow": 1,
                "isTop": 0,
                "likes": 0,
                "productId": 10086102942203,
                "replies": [
                    {
                        "headImage": "https://res.vmallres.com/nwap/20170828/images/echannelWap/misc/defaultface_customer_service.png",
                        "headImageDb": "",
                        "likes": 0,
                        "parentId": 0,
                        "replyContent": "哦哟，这评论里的情侣又多，又喜欢秀恩爱，本单身狗超喜欢这里的。",
                        "replyId": 81559684937143,
                        "replyTime": "2019-09-30 23:28:05+0800",
                        "replyerName": "华为商城客服",
                        "type": 0
                    }
                ],
                "replyCount": 1,
                "score": 5,
                "showImageCount": 0,
                "skuAttrs": "嫣紫色,全网通 8GB+128GB,官方标配",
                "skuCode": "2601010102623",
                "skuName": "HUAWEI P30 Pro 麒麟980 超感光徕卡四摄 屏内指纹 双景录像 8GB+128GB 全网通版 (嫣紫色)",
                "tags": [],
                "title": "",
                "type": 0,
                "userName": "冰****"
            },
            {
                "canReply": "0",
                "commentId": 81529015094805,
                "commentLevel": "好评",
                "content": "说实话第一次用华为      物流比较慢  让我等的很焦急    但是收到后  打开   所有焦急感都没了    实在好看    性能好的不行  顺畅     续航也很牛       拍照更没的说了   非常好    各方面都非常好     第一次用两下就清楚手机功能了",
                "creationTime": "2019-09-30 14:56:55+0800",
                "gradeCode": 3,
                "headImage": "https://res.vmallres.com/nwap/20170828/images/echannelWap/misc/defaultface_user_after.png",
                "headImageDb": "",
                "images": [],
                "isAnonymous": 1,
                "isShow": 1,
                "isTop": 0,
                "likes": 0,
                "productId": 10086102942203,
                "replies": [],
                "replyCount": 0,
                "score": 5,
                "showImageCount": 0,
                "skuAttrs": "天空之境,全网通 8GB+128GB,官方标配",
                "skuCode": "2601010102603",
                "skuName": "HUAWEI P30 Pro 麒麟980 超感光徕卡四摄 屏内指纹 双景录像 8GB+128GB 全网通版（天空之境）",
                "tags": [],
                "title": "",
                "type": 0,
                "userName": "强*"
            },
            {
                "canReply": "0",
                "commentId": 81528532368175,
                "commentLevel": "好评",
                "content": "用了一个多月了，第一次用p系列的还不错的体验。",
                "creationTime": "2019-09-30 14:48:52+0800",
                "gradeCode": 3,
                "headImage": "https://res.vmallres.com/nwap/20170828/images/echannelWap/misc/defaultface_user_after.png",
                "headImageDb": "",
                "images": [
                    {
                        "id": 81528532368176,
                        "large": "https://res.vmallres.com/rms/comment/image/U0464/59a4f061952bf45b073b3aedc1e337c4/1080/78e519f6f7619d46e6f74e73.jpg",
                        "small": "https://res.vmallres.com/rms/comment/image/U0464/59a4f061952bf45b073b3aedc1e337c4/100/78e519f6f7619d46e6f74e73.jpg"
                    }
                ],
                "isAnonymous": 1,
                "isShow": 1,
                "isTop": 0,
                "likes": 0,
                "productId": 10086102942203,
                "replies": [],
                "replyCount": 0,
                "score": 5,
                "showImageCount": 0,
                "skuAttrs": "天空之境,全网通 8GB+128GB,官方标配",
                "skuCode": "2601010102603",
                "skuName": "HUAWEI P30 Pro 麒麟980 超感光徕卡四摄 屏内指纹 双景录像 8GB+128GB 全网通版（天空之境）",
                "tags": [],
                "title": "",
                "type": 0,
                "userName": "皮***"
            },
            {
                "canReply": "0",
                "commentId": 81528339200784,
                "commentLevel": "好评",
                "content": "用户未填写评价内容",
                "creationTime": "2019-09-30 14:45:39+0800",
                "gradeCode": 0,
                "headImage": "https://res.vmallres.com/rms/comment/image/U0875/20ab3e0079e8376dd11b2da097d06e54/d667dc17ce4c333967e90675.jpg",
                "headImageDb": "",
                "images": [],
                "isAnonymous": 1,
                "isShow": 1,
                "isTop": 0,
                "likes": 0,
                "productId": 10086102942203,
                "replies": [],
                "replyCount": 0,
                "score": 5,
                "showImageCount": 0,
                "skuAttrs": "极光色,全网通 8GB+512GB,官方标配",
                "skuCode": "2601010102612",
                "skuName": "HUAWEI P30 Pro 麒麟980 超感光徕卡四摄 屏内指纹 曲面屏 双景录像 8GB+512GB 全网通版（极光色）",
                "tags": [],
                "title": "",
                "type": 0,
                "userName": "D****"
            }
        ],
        "count": 112554,
        "defaultGoodCount": 29254,
        "goodCount": 111417,
        "goodRate": "0.99",
        "hasImageCount": 22221,
        "hide": 0,
        "hotTags": [],
        "loginCount": 0,
        "loginImageCount": 0,
        "loginTopCount": 0,
        "normalCount": 437,
        "normalRate": "0.0",
        "page": {
            "firstRow": 5740,
            "pageNum": 288,
            "pageSize": 20,
            "totalPage": 4165,
            "totalRow": 83300,
            "version": 0
        },
        "pid": 10086102942203,
        "pids": [
            10086102942203,
            10086576121185,
            10086036045937,
            10086092865372,
            10086567879532,
            10086570832735,
            10086303797167,
            10086198945779,
            10086490067095,
            10086440129759,
            10086442456543,
            10086921421590,
            10086777387906,
            10086204790435,
            10086450832279,
            10086113196785,
            10086321031701,
            10086336387965,
            10086809756853,
            10086314958628,
            10086447575491,
            10086501288078,
            10086490521968,
            10086025336801,
            10086970558808,
            10086091766908
        ],
        "score1Count": 700,
        "score2Count": 145,
        "score3Count": 292,
        "score4Count": 532,
        "score5Count": 81631,
        "systemTagList": [
            {
                "count": 88,
                "tagId": 10000001,
                "tagName": "外观不错"
            },
            {
                "count": 84,
                "tagId": 10050001,
                "tagName": "拍照不错"
            },
            {
                "count": 80,
                "tagId": 10080001,
                "tagName": "物流不错"
            },
            {
                "count": 51,
                "tagId": 10070001,
                "tagName": "电池不错"
            },
            {
                "count": 49,
                "tagId": 10040001,
                "tagName": "手感好"
            },
            {
                "count": 26,
                "tagId": 10110001,
                "tagName": "活动给力"
            },
            {
                "count": 22,
                "tagId": 10030001,
                "tagName": "性价比高"
            },
            {
                "count": 15,
                "tagId": 10010001,
                "tagName": "屏幕不错"
            },
            {
                "count": 9,
                "tagId": 10020001,
                "tagName": "内存很好"
            },
            {
                "count": 7,
                "tagId": 10090001,
                "tagName": "服务好"
            },
            {
                "count": 6,
                "tagId": 10150001,
                "tagName": "音质很好"
            },
            {
                "count": 4,
                "tagId": 10130001,
                "tagName": "指纹识别不错"
            },
            {
                "count": 4,
                "tagId": 10120001,
                "tagName": "信号不错"
            }
        ],
        "topCount": 9331
    },
    "info": "成功",
    "resultCode": "0"
}