{
    "rateDetail": {
        "rateCount": {
            "total": 45110,
            "shop": 0,
            "picNum": 14447,
            "used": 5361
        },
        "rateDanceInfo": {
            "storeType": 4,
            "currentMilles": 1584369565231,
            "showChooseTopic": false,
            "intervalMilles": 7593193620
        },
        "rateList": [
            {
                "auctionPicUrl": "",
                "userInfo": "",
                "displayRatePic": "",
                "dsr": 0,
                "displayRateSum": 0,
                "appendComment": null,
                "fromMemory": 0,
                "picsSmall": [],
                "tmallSweetPic": "",
                "rateDate": "2020-03-12 17:59:56",
                "rateContent": "音质很好 操作流畅",
                "fromMall": true,
                "userIdEncryption": "",
                "sellerId": 2838892713,
                "videoList": [],
                "displayUserLink": "",
                "id": 1076821605550,
                "aliMallSeller": false,
                "reply": "",
                "pics": [],
                "buyCount": 0,
                "userVipLevel": 0,
                "auctionSku": "网络类型:4G全网通;机身颜色:亮黑色;套餐类型:官方标配;存储容量:8+128GB",
                "anony": true,
                "displayUserNumId": 0,
                "goldUser": false,
                "attributesMap": null,
                "tradeEndTime": {
                    "date": 12,
                    "hours": 17,
                    "seconds": 52,
                    "month": 2,
                    "timezoneOffset": -480,
                    "year": 120,
                    "minutes": 56,
                    "time": 1584007012000,
                    "day": 4
                },
                "headExtraPic": "",
                "aucNumId": 0,
                "displayUserNick": "t***4",
                "structuredRateList": [],
                "carServiceLocation": "",
                "userVipPic": "",
                "serviceRateContent": "",
                "memberIcon": "",
                "attributes": "",
                "position": "721-11-5,9;30221-11-0,4;",
                "cmsSource": "天猫",
                "tamllSweetLevel": 0,
                "gmtCreateTime": {
                    "date": 12,
                    "hours": 17,
                    "seconds": 56,
                    "month": 2,
                    "timezoneOffset": -480,
                    "year": 120,
                    "minutes": 59,
                    "time": 1584007196000,
                    "day": 4
                },
                "useful": true,
                "displayUserRateLink": ""
            },
            {
                "auctionPicUrl": "",
                "userInfo": "",
                "displayRatePic": "",
                "dsr": 0,
                "displayRateSum": 0,
                "appendComment": null,
                "fromMemory": 0,
                "picsSmall": [],
                "tmallSweetPic": "",
                "rateDate": "2020-03-12 17:08:18",
                "rateContent": "拍照效果：像素还是很好的 拍出来也很有大片感觉 就是专业模式不太会调那些参数 摄影**就是我了 我见有人喷自拍效果不好 我也试了 也许只是因为他们没有找到技巧？ 电池续航：超级耐用！！！！上了一整天网课只用了一半 充电速度杠杠的简直十分钟肉眼可见的  运行速度：非常流畅 通信音质：音质也很赞啊 颜值方面 珠光贝母绝对适合女孩子哦！看起来是白色 但是随着光线角度的变化会出现渐变效果！ 如果有小伙伴担心手机是不是正品全新机 不用担心啦 因为我曾经也是担心的其中一员 事实是旗舰店没有让我失望呀！闭着眼放心买！",
                "fromMall": true,
                "userIdEncryption": "",
                "sellerId": 2838892713,
                "videoList": [],
                "displayUserLink": "",
                "id": 1076564308578,
                "aliMallSeller": false,
                "reply": "",
                "pics": [],
                "buyCount": 0,
                "userVipLevel": 0,
                "auctionSku": "网络类型:4G全网通;机身颜色:珠光贝母;套餐类型:官方标配;存储容量:8+256GB",
                "anony": false,
                "displayUserNumId": 0,
                "goldUser": false,
                "attributesMap": null,
                "tradeEndTime": {
                    "date": 10,
                    "hours": 14,
                    "seconds": 44,
                    "month": 2,
                    "timezoneOffset": -480,
                    "year": 120,
                    "minutes": 24,
                    "time": 1583821484000,
                    "day": 2
                },
                "headExtraPic": "",
                "aucNumId": 0,
                "displayUserNick": "l***l",
                "structuredRateList": [],
                "carServiceLocation": "",
                "userVipPic": "",
                "serviceRateContent": "",
                "memberIcon": "",
                "attributes": "",
                "position": "",
                "cmsSource": "天猫",
                "tamllSweetLevel": 0,
                "gmtCreateTime": {
                    "date": 12,
                    "hours": 17,
                    "seconds": 18,
                    "month": 2,
                    "timezoneOffset": -480,
                    "year": 120,
                    "minutes": 8,
                    "time": 1584004098000,
                    "day": 4
                },
                "useful": true,
                "displayUserRateLink": ""
            },
            {
                "auctionPicUrl": "",
                "userInfo": "",
                "displayRatePic": "",
                "dsr": 0,
                "displayRateSum": 0,
                "appendComment": null,
                "fromMemory": 0,
                "picsSmall": [],
                "tmallSweetPic": "tmall-grade-t4-18.png",
                "rateDate": "2020-03-12 16:57:13",
                "rateContent": "货很快收到了，还不错！性价比高！喜欢！希望刚买不要再掉价钱了，不然又会伤心",
                "fromMall": true,
                "userIdEncryption": "",
                "sellerId": 2838892713,
                "videoList": [],
                "displayUserLink": "",
                "id": 1076814841985,
                "aliMallSeller": false,
                "reply": "",
                "pics": [],
                "buyCount": 0,
                "userVipLevel": 0,
                "auctionSku": "网络类型:4G全网通;机身颜色:极光色;套餐类型:官方标配;存储容量:8+256GB",
                "anony": false,
                "displayUserNumId": 0,
                "goldUser": true,
                "attributesMap": null,
                "tradeEndTime": {
                    "date": 12,
                    "hours": 16,
                    "seconds": 8,
                    "month": 2,
                    "timezoneOffset": -480,
                    "year": 120,
                    "minutes": 55,
                    "time": 1584003308000,
                    "day": 4
                },
                "headExtraPic": "",
                "aucNumId": 0,
                "displayUserNick": "樊***9",
                "structuredRateList": [],
                "carServiceLocation": "",
                "userVipPic": "",
                "serviceRateContent": "",
                "memberIcon": "",
                "attributes": "",
                "position": "920-11-16,18;20520-11-11,15;920-11-7,10;",
                "cmsSource": "天猫",
                "tamllSweetLevel": 4,
                "gmtCreateTime": {
                    "date": 12,
                    "hours": 16,
                    "seconds": 13,
                    "month": 2,
                    "timezoneOffset": -480,
                    "year": 120,
                    "minutes": 57,
                    "time": 1584003433000,
                    "day": 4
                },
                "useful": true,
                "displayUserRateLink": ""
            },
            {
                "auctionPicUrl": "",
                "userInfo": "",
                "displayRatePic": "",
                "dsr": 0,
                "displayRateSum": 0,
                "appendComment": null,
                "fromMemory": 0,
                "picsSmall": [],
                "tmallSweetPic": "tmall-grade-t2-18.png",
                "rateDate": "2020-03-12 16:27:07",
                "rateContent": "拍照效果：很喜欢",
                "fromMall": true,
                "userIdEncryption": "",
                "sellerId": 2838892713,
                "videoList": [],
                "displayUserLink": "",
                "id": 1077316299520,
                "aliMallSeller": false,
                "reply": "",
                "pics": [],
                "buyCount": 0,
                "userVipLevel": 0,
                "auctionSku": "网络类型:4G全网通;机身颜色:珠光贝母;套餐类型:官方标配;存储容量:8+256GB",
                "anony": false,
                "displayUserNumId": 0,
                "goldUser": false,
                "attributesMap": null,
                "tradeEndTime": {
                    "date": 12,
                    "hours": 16,
                    "seconds": 40,
                    "month": 2,
                    "timezoneOffset": -480,
                    "year": 120,
                    "minutes": 26,
                    "time": 1584001600000,
                    "day": 4
                },
                "headExtraPic": "",
                "aucNumId": 0,
                "displayUserNick": "t***7",
                "structuredRateList": [],
                "carServiceLocation": "",
                "userVipPic": "",
                "serviceRateContent": "",
                "memberIcon": "",
                "attributes": "",
                "position": "111;620-12-0,4;920-11-5,8;",
                "cmsSource": "天猫",
                "tamllSweetLevel": 2,
                "gmtCreateTime": {
                    "date": 12,
                    "hours": 16,
                    "seconds": 7,
                    "month": 2,
                    "timezoneOffset": -480,
                    "year": 120,
                    "minutes": 27,
                    "time": 1584001627000,
                    "day": 4
                },
                "useful": true,
                "displayUserRateLink": ""
            },
            {
                "auctionPicUrl": "",
                "userInfo": "",
                "displayRatePic": "",
                "dsr": 0,
                "displayRateSum": 0,
                "appendComment": null,
                "fromMemory": 0,
                "picsSmall": [],
                "tmallSweetPic": "tmall-grade-t3-18.png",
                "rateDate": "2020-03-12 15:59:30",
                "rateContent": "拍照效果：好 显示效果：好 电池续航：华为的电池没话说 通信音质：挺好的",
                "fromMall": true,
                "userIdEncryption": "",
                "sellerId": 2838892713,
                "videoList": [],
                "displayUserLink": "",
                "id": 1077313395435,
                "aliMallSeller": false,
                "reply": "",
                "pics": [],
                "buyCount": 0,
                "userVipLevel": 0,
                "auctionSku": "网络类型:4G全网通;机身颜色:珠光贝母;套餐类型:官方标配;存储容量:8+256GB",
                "anony": false,
                "displayUserNumId": 0,
                "goldUser": true,
                "attributesMap": null,
                "tradeEndTime": {
                    "date": 10,
                    "hours": 9,
                    "seconds": 0,
                    "month": 2,
                    "timezoneOffset": -480,
                    "year": 120,
                    "minutes": 43,
                    "time": 1583804580000,
                    "day": 2
                },
                "headExtraPic": "",
                "aucNumId": 0,
                "displayUserNick": "最***果",
                "structuredRateList": [],
                "carServiceLocation": "",
                "userVipPic": "",
                "serviceRateContent": "",
                "memberIcon": "",
                "attributes": "",
                "position": "920-11-33,36;920-11-12,13;620-12-0,4;20521-12-14,18;30221-12-28,32;521-11-19,27;920-11-5,6;620-12-7,11;",
                "cmsSource": "天猫",
                "tamllSweetLevel": 3,
                "gmtCreateTime": {
                    "date": 12,
                    "hours": 15,
                    "seconds": 30,
                    "month": 2,
                    "timezoneOffset": -480,
                    "year": 120,
                    "minutes": 59,
                    "time": 1583999970000,
                    "day": 4
                },
                "useful": true,
                "displayUserRateLink": ""
            },
            {
                "auctionPicUrl": "",
                "userInfo": "",
                "displayRatePic": "",
                "dsr": 0,
                "displayRateSum": 0,
                "appendComment": null,
                "fromMemory": 0,
                "picsSmall": [],
                "tmallSweetPic": "tmall-grade-t2-18.png",
                "rateDate": "2020-03-12 15:02:15",
                "rateContent": "其他特色：颜色超喜欢，曲屏手感超棒 拍照效果：拍照真的很棒 电池续航：电池耐用 运行速度：无语，好用就完事儿了",
                "fromMall": true,
                "userIdEncryption": "",
                "sellerId": 2838892713,
                "videoList": [],
                "displayUserLink": "",
                "id": 1077307819374,
                "aliMallSeller": false,
                "reply": "",
                "pics": [
                    "//img.alicdn.com/bao/uploaded/i4/O1CN01FHBmdA2GR5XHYEaZC_!!0-rate.jpg"
                ],
                "buyCount": 0,
                "userVipLevel": 0,
                "auctionSku": "网络类型:4G全网通;机身颜色:珠光贝母;套餐类型:官方标配;存储容量:8+128GB",
                "anony": false,
                "displayUserNumId": 0,
                "goldUser": false,
                "attributesMap": null,
                "tradeEndTime": {
                    "date": 9,
                    "hours": 20,
                    "seconds": 9,
                    "month": 2,
                    "timezoneOffset": -480,
                    "year": 120,
                    "minutes": 41,
                    "time": 1583757669000,
                    "day": 1
                },
                "headExtraPic": "",
                "aucNumId": 0,
                "displayUserNick": "d***子",
                "structuredRateList": [],
                "carServiceLocation": "",
                "userVipPic": "",
                "serviceRateContent": "",
                "memberIcon": "",
                "attributes": "",
                "position": "40221-11-23,29;20521-12-30,34;620-12-18,22;521-11-35,39;921-12-40,44;721-11-11,17;920-11-5,10;",
                "cmsSource": "天猫",
                "tamllSweetLevel": 2,
                "gmtCreateTime": {
                    "date": 12,
                    "hours": 15,
                    "seconds": 15,
                    "month": 2,
                    "timezoneOffset": -480,
                    "year": 120,
                    "minutes": 2,
                    "time": 1583996535000,
                    "day": 4
                },
                "useful": true,
                "displayUserRateLink": ""
            },
            {
                "auctionPicUrl": "",
                "userInfo": "",
                "displayRatePic": "",
                "dsr": 0,
                "displayRateSum": 0,
                "appendComment": null,
                "fromMemory": 0,
                "picsSmall": [],
                "tmallSweetPic": "tmall-grade-t2-18.png",
                "rateDate": "2020-03-12 13:21:36",
                "rateContent": "拍照效果：还OK 电池续航：目前基本能用两天 充电是快充 一个小时不用就充好了 运行速度：还OK 比较快 其他特色：总体还可以吧 24期免息分期 也挺好",
                "fromMall": true,
                "userIdEncryption": "",
                "sellerId": 2838892713,
                "videoList": [],
                "displayUserLink": "",
                "id": 1077297675246,
                "aliMallSeller": false,
                "reply": "",
                "pics": [],
                "buyCount": 0,
                "userVipLevel": 0,
                "auctionSku": "网络类型:4G全网通;机身颜色:赤茶橘;套餐类型:官方标配;存储容量:8+256GB",
                "anony": false,
                "displayUserNumId": 0,
                "goldUser": true,
                "attributesMap": null,
                "tradeEndTime": {
                    "date": 12,
                    "hours": 13,
                    "seconds": 51,
                    "month": 2,
                    "timezoneOffset": -480,
                    "year": 120,
                    "minutes": 19,
                    "time": 1583990391000,
                    "day": 4
                },
                "headExtraPic": "",
                "aucNumId": 0,
                "displayUserNick": "h***y",
                "structuredRateList": [],
                "carServiceLocation": "",
                "userVipPic": "",
                "serviceRateContent": "",
                "memberIcon": "",
                "attributes": "",
                "position": "921-11-49,52;620-11-58,64;920-11-29,39;920-11-45,48;620-12-0,4;20521-12-9,13;920-11-73,76;921-12-40,44;920-11-5,8;10521-11-23,28;",
                "cmsSource": "天猫",
                "tamllSweetLevel": 2,
                "gmtCreateTime": {
                    "date": 12,
                    "hours": 13,
                    "seconds": 36,
                    "month": 2,
                    "timezoneOffset": -480,
                    "year": 120,
                    "minutes": 21,
                    "time": 1583990496000,
                    "day": 4
                },
                "useful": true,
                "displayUserRateLink": ""
            },
            {
                "auctionPicUrl": "",
                "userInfo": "",
                "displayRatePic": "",
                "dsr": 0,
                "displayRateSum": 0,
                "appendComment": null,
                "fromMemory": 0,
                "picsSmall": [],
                "tmallSweetPic": "tmall-grade-t4-18.png",
                "rateDate": "2020-03-12 12:55:08",
                "rateContent": "颜值高，拍照效果好，运行速度快！支持华为，希望早日追赶上苹果",
                "fromMall": true,
                "userIdEncryption": "",
                "sellerId": 2838892713,
                "videoList": [],
                "displayUserLink": "",
                "id": 1076538744243,
                "aliMallSeller": false,
                "reply": "",
                "pics": [],
                "buyCount": 0,
                "userVipLevel": 0,
                "auctionSku": "网络类型:4G全网通;机身颜色:天空之境;套餐类型:官方标配;存储容量:8+128GB",
                "anony": false,
                "displayUserNumId": 0,
                "goldUser": false,
                "attributesMap": null,
                "tradeEndTime": {
                    "date": 9,
                    "hours": 16,
                    "seconds": 35,
                    "month": 2,
                    "timezoneOffset": -480,
                    "year": 120,
                    "minutes": 57,
                    "time": 1583744255000,
                    "day": 1
                },
                "headExtraPic": "",
                "aucNumId": 0,
                "displayUserNick": "c***e",
                "structuredRateList": [],
                "carServiceLocation": "",
                "userVipPic": "",
                "serviceRateContent": "",
                "memberIcon": "",
                "attributes": "",
                "position": "920-11-16,20;920-12-0,3;921-11-10,15;40221-11-4,9;",
                "cmsSource": "天猫",
                "tamllSweetLevel": 4,
                "gmtCreateTime": {
                    "date": 12,
                    "hours": 12,
                    "seconds": 8,
                    "month": 2,
                    "timezoneOffset": -480,
                    "year": 120,
                    "minutes": 55,
                    "time": 1583988908000,
                    "day": 4
                },
                "useful": true,
                "displayUserRateLink": ""
            },
            {
                "auctionPicUrl": "",
                "userInfo": "",
                "displayRatePic": "",
                "dsr": 0,
                "displayRateSum": 0,
                "appendComment": null,
                "fromMemory": 0,
                "picsSmall": [],
                "tmallSweetPic": "tmall-grade-t3-18.png",
                "rateDate": "2020-03-12 12:44:16",
                "rateContent": "指纹按键！真不好用，对不起这个价格",
                "fromMall": true,
                "userIdEncryption": "",
                "sellerId": 2838892713,
                "videoList": [],
                "displayUserLink": "",
                "id": 1076789369569,
                "aliMallSeller": false,
                "reply": "让快乐细水长流，心里无忧无愁~针对您反馈的问题，建议在上下滑动、左右滑动指纹时，保持匀速滑动。并且保持手指滑动距离最好完全覆盖指纹传感器区域，以提高系统识别正确率。建议按压指纹时，尽量保持手指与指纹区域垂直快速大面积按压。如您在后续使用中存在问题，您可以随时进线咨询在线客服，我们全力为您解答。携一片蓝天一朵白云，祝您每天好心情！",
                "pics": [],
                "buyCount": 0,
                "userVipLevel": 0,
                "auctionSku": "网络类型:4G全网通;机身颜色:天空之境;套餐类型:官方标配;存储容量:8+128GB",
                "anony": false,
                "displayUserNumId": 0,
                "goldUser": true,
                "attributesMap": null,
                "tradeEndTime": {
                    "date": 5,
                    "hours": 14,
                    "seconds": 28,
                    "month": 2,
                    "timezoneOffset": -480,
                    "year": 120,
                    "minutes": 42,
                    "time": 1583390548000,
                    "day": 4
                },
                "headExtraPic": "",
                "aucNumId": 0,
                "displayUserNick": "物***8",
                "structuredRateList": [],
                "carServiceLocation": "",
                "userVipPic": "",
                "serviceRateContent": "",
                "memberIcon": "",
                "attributes": "",
                "position": "920-13-5,9;821-12-0,4;520-12-10,17;",
                "cmsSource": "天猫",
                "tamllSweetLevel": 3,
                "gmtCreateTime": {
                    "date": 12,
                    "hours": 12,
                    "seconds": 16,
                    "month": 2,
                    "timezoneOffset": -480,
                    "year": 120,
                    "minutes": 44,
                    "time": 1583988256000,
                    "day": 4
                },
                "useful": true,
                "displayUserRateLink": ""
            },
            {
                "auctionPicUrl": "",
                "userInfo": "",
                "displayRatePic": "",
                "dsr": 0,
                "displayRateSum": 0,
                "appendComment": null,
                "fromMemory": 0,
                "picsSmall": [],
                "tmallSweetPic": "tmall-grade-t2-18.png",
                "rateDate": "2020-03-12 12:44:14",
                "rateContent": "挺好的，就是之前用的苹果7，屏突然变大，重量增加，有点不适应",
                "fromMall": true,
                "userIdEncryption": "",
                "sellerId": 2838892713,
                "videoList": [],
                "displayUserLink": "",
                "id": 1076537728486,
                "aliMallSeller": false,
                "reply": "让快乐细水长流，心里无忧无愁~手机屏幕大用着霸气，看着贵气，大屏大世界，看的见的尽在华为里。观影简直是一场视觉盛宴。亲爱哒，一回生两回熟，宝贝与您日夜相随，相信您很快就会习惯并逐渐发现机子的好性能，爱不释手呢。在使用中有任何的问题，欢迎您随时联系我们的在线客服，乐意为您效劳哟。晴天雨天阴天，愿您快乐每天~",
                "pics": [],
                "buyCount": 0,
                "userVipLevel": 0,
                "auctionSku": "网络类型:4G全网通;机身颜色:珠光贝母;套餐类型:官方标配;存储容量:8+128GB",
                "anony": false,
                "displayUserNumId": 0,
                "goldUser": false,
                "attributesMap": null,
                "tradeEndTime": {
                    "date": 3,
                    "hours": 20,
                    "seconds": 24,
                    "month": 2,
                    "timezoneOffset": -480,
                    "year": 120,
                    "minutes": 35,
                    "time": 1583238924000,
                    "day": 2
                },
                "headExtraPic": "",
                "aucNumId": 0,
                "displayUserNick": "点***融",
                "structuredRateList": [],
                "carServiceLocation": "",
                "userVipPic": "",
                "serviceRateContent": "",
                "memberIcon": "",
                "attributes": "",
                "position": "111;421-12-14,19;920-11-0,3;721-12-20,24;",
                "cmsSource": "天猫",
                "tamllSweetLevel": 2,
                "gmtCreateTime": {
                    "date": 12,
                    "hours": 12,
                    "seconds": 14,
                    "month": 2,
                    "timezoneOffset": -480,
                    "year": 120,
                    "minutes": 44,
                    "time": 1583988254000,
                    "day": 4
                },
                "useful": true,
                "displayUserRateLink": ""
            },
            {
                "auctionPicUrl": "",
                "userInfo": "",
                "displayRatePic": "",
                "dsr": 0,
                "displayRateSum": 0,
                "appendComment": null,
                "fromMemory": 0,
                "picsSmall": [],
                "tmallSweetPic": "tmall-grade-t3-18.png",
                "rateDate": "2020-03-12 12:33:34",
                "rateContent": "拍照效果：清晰，超广角",
                "fromMall": true,
                "userIdEncryption": "",
                "sellerId": 2838892713,
                "videoList": [],
                "displayUserLink": "",
                "id": 1076788101707,
                "aliMallSeller": false,
                "reply": "",
                "pics": [],
                "buyCount": 0,
                "userVipLevel": 0,
                "auctionSku": "网络类型:4G全网通;机身颜色:天空之境;套餐类型:官方标配;存储容量:8+256GB",
                "anony": false,
                "displayUserNumId": 0,
                "goldUser": true,
                "attributesMap": null,
                "tradeEndTime": {
                    "date": 7,
                    "hours": 20,
                    "seconds": 0,
                    "month": 2,
                    "timezoneOffset": -480,
                    "year": 120,
                    "minutes": 30,
                    "time": 1583584200000,
                    "day": 6
                },
                "headExtraPic": "",
                "aucNumId": 0,
                "displayUserNick": "t***8",
                "structuredRateList": [],
                "carServiceLocation": "",
                "userVipPic": "",
                "serviceRateContent": "",
                "memberIcon": "",
                "attributes": "",
                "position": "620-12-0,4;920-11-5,7;",
                "cmsSource": "天猫",
                "tamllSweetLevel": 3,
                "gmtCreateTime": {
                    "date": 12,
                    "hours": 12,
                    "seconds": 34,
                    "month": 2,
                    "timezoneOffset": -480,
                    "year": 120,
                    "minutes": 33,
                    "time": 1583987614000,
                    "day": 4
                },
                "useful": true,
                "displayUserRateLink": ""
            },
            {
                "auctionPicUrl": "",
                "userInfo": "",
                "displayRatePic": "",
                "dsr": 0,
                "displayRateSum": 0,
                "appendComment": null,
                "fromMemory": 0,
                "picsSmall": [],
                "tmallSweetPic": "tmall-grade-t3-18.png",
                "rateDate": "2020-03-12 12:20:40",
                "rateContent": "这个保护膜上有带水纹，我这还沒收到货就降价了，信息也是机器回",
                "fromMall": true,
                "userIdEncryption": "",
                "sellerId": 2838892713,
                "videoList": [],
                "displayUserLink": "",
                "id": 1076787229075,
                "aliMallSeller": false,
                "reply": "聆听到您的心声，小的立马踏云而来，请您息怒～经确认，我们有工作人员已经电话联系过您，咱们店铺内有服务助手和人工客服，一般来访会先由服务助手接待，可以回答简单的问题。如果需要联系在线客服，可在对话面板输入&ldquo;人工客服&rdquo;即可转接哦，其商品价格随市场价格的波动会有涨价、降价或者优惠等变化，您可以多关注我们店铺的活动更新，一些节日或大促期间都有活动优惠噢，若后续使用有疑问可随时咨询客服。希望华为伴您生活好心情~",
                "pics": [],
                "buyCount": 0,
                "userVipLevel": 0,
                "auctionSku": "网络类型:4G全网通;机身颜色:珠光贝母;套餐类型:官方标配;存储容量:8+256GB",
                "anony": false,
                "displayUserNumId": 0,
                "goldUser": true,
                "attributesMap": null,
                "tradeEndTime": {
                    "date": 12,
                    "hours": 12,
                    "seconds": 48,
                    "month": 2,
                    "timezoneOffset": -480,
                    "year": 120,
                    "minutes": 17,
                    "time": 1583986668000,
                    "day": 4
                },
                "headExtraPic": "",
                "aucNumId": 0,
                "displayUserNick": "金***君",
                "structuredRateList": [],
                "carServiceLocation": "",
                "userVipPic": "",
                "serviceRateContent": "",
                "memberIcon": "",
                "attributes": "",
                "position": "621-12-0,10;520-12-11,22;620-12-23,30;",
                "cmsSource": "天猫",
                "tamllSweetLevel": 3,
                "gmtCreateTime": {
                    "date": 12,
                    "hours": 12,
                    "seconds": 40,
                    "month": 2,
                    "timezoneOffset": -480,
                    "year": 120,
                    "minutes": 20,
                    "time": 1583986840000,
                    "day": 4
                },
                "useful": true,
                "displayUserRateLink": ""
            },
            {
                "auctionPicUrl": "",
                "userInfo": "",
                "displayRatePic": "",
                "dsr": 0,
                "displayRateSum": 0,
                "appendComment": null,
                "fromMemory": 0,
                "picsSmall": [],
                "tmallSweetPic": "tmall-grade-t2-18.png",
                "rateDate": "2020-03-12 11:59:06",
                "rateContent": "买错了！想买魅特30！ 结果买了一个这个！凑合用吧！",
                "fromMall": true,
                "userIdEncryption": "",
                "sellerId": 2838892713,
                "videoList": [],
                "displayUserLink": "",
                "id": 1076784925898,
                "aliMallSeller": false,
                "reply": "阳光缕缕照心房，赶走烦恼心飞扬~HUAWEI P30 Pro搭载超感光徕卡四摄系统，第一次在手机上配置超感光传感器和潜望式镜头组合，从底层突破感光与距离的限制。超感光传感器改写4000万像素结构，在黑暗中汇聚光明，夜幕中举起手机就能拍出栩栩如生、细节清晰的夜景照片和视频。也是很不错的哦，且我们是华为官方旗舰店，我们会严格遵照三包法，维护消费者合法权益的哦，请您放心呢。如您在后续使用中存在疑问，您可以进线咨询在线客服，我们全力为您解答。晴天雨天阴天，愿您快乐每天~",
                "pics": [],
                "buyCount": 0,
                "userVipLevel": 0,
                "auctionSku": "网络类型:4G全网通;机身颜色:天空之境;套餐类型:官方标配;存储容量:8+128GB",
                "anony": false,
                "displayUserNumId": 0,
                "goldUser": false,
                "attributesMap": null,
                "tradeEndTime": {
                    "date": 12,
                    "hours": 11,
                    "seconds": 5,
                    "month": 2,
                    "timezoneOffset": -480,
                    "year": 120,
                    "minutes": 58,
                    "time": 1583985485000,
                    "day": 4
                },
                "headExtraPic": "",
                "aucNumId": 0,
                "displayUserNick": "极***5",
                "structuredRateList": [],
                "carServiceLocation": "",
                "userVipPic": "",
                "serviceRateContent": "",
                "memberIcon": "",
                "attributes": "",
                "position": "920-13-0,3;",
                "cmsSource": "天猫",
                "tamllSweetLevel": 2,
                "gmtCreateTime": {
                    "date": 12,
                    "hours": 11,
                    "seconds": 6,
                    "month": 2,
                    "timezoneOffset": -480,
                    "year": 120,
                    "minutes": 59,
                    "time": 1583985546000,
                    "day": 4
                },
                "useful": true,
                "displayUserRateLink": ""
            },
            {
                "auctionPicUrl": "",
                "userInfo": "",
                "displayRatePic": "",
                "dsr": 0,
                "displayRateSum": 0,
                "appendComment": null,
                "fromMemory": 0,
                "picsSmall": [],
                "tmallSweetPic": "",
                "rateDate": "2020-03-12 11:51:42",
                "rateContent": "超级超级超级好看！！！！",
                "fromMall": true,
                "userIdEncryption": "",
                "sellerId": 2838892713,
                "videoList": [],
                "displayUserLink": "",
                "id": 1077037742899,
                "aliMallSeller": false,
                "reply": "",
                "pics": [],
                "buyCount": 0,
                "userVipLevel": 0,
                "auctionSku": "网络类型:4G全网通;机身颜色:天空之境;套餐类型:官方标配;存储容量:8+128GB",
                "anony": false,
                "displayUserNumId": 0,
                "goldUser": false,
                "attributesMap": null,
                "tradeEndTime": {
                    "date": 4,
                    "hours": 12,
                    "seconds": 50,
                    "month": 2,
                    "timezoneOffset": -480,
                    "year": 120,
                    "minutes": 19,
                    "time": 1583295590000,
                    "day": 3
                },
                "headExtraPic": "",
                "aucNumId": 0,
                "displayUserNick": "t***9",
                "structuredRateList": [],
                "carServiceLocation": "",
                "userVipPic": "",
                "serviceRateContent": "",
                "memberIcon": "",
                "attributes": "",
                "position": "121-11-0,8;",
                "cmsSource": "天猫",
                "tamllSweetLevel": 0,
                "gmtCreateTime": {
                    "date": 12,
                    "hours": 11,
                    "seconds": 42,
                    "month": 2,
                    "timezoneOffset": -480,
                    "year": 120,
                    "minutes": 51,
                    "time": 1583985102000,
                    "day": 4
                },
                "useful": true,
                "displayUserRateLink": ""
            },
            {
                "auctionPicUrl": "",
                "userInfo": "",
                "displayRatePic": "",
                "dsr": 0,
                "displayRateSum": 0,
                "appendComment": null,
                "fromMemory": 0,
                "picsSmall": [],
                "tmallSweetPic": "",
                "rateDate": "2020-03-12 11:35:56",
                "rateContent": "很好看，我老婆很喜欢。",
                "fromMall": true,
                "userIdEncryption": "",
                "sellerId": 2838892713,
                "videoList": [],
                "displayUserLink": "",
                "id": 1076783113094,
                "aliMallSeller": false,
                "reply": "",
                "pics": [],
                "buyCount": 0,
                "userVipLevel": 0,
                "auctionSku": "网络类型:4G全网通;机身颜色:赤茶橘;套餐类型:官方标配;存储容量:8+256GB",
                "anony": false,
                "displayUserNumId": 0,
                "goldUser": false,
                "attributesMap": null,
                "tradeEndTime": {
                    "date": 10,
                    "hours": 12,
                    "seconds": 15,
                    "month": 2,
                    "timezoneOffset": -480,
                    "year": 120,
                    "minutes": 31,
                    "time": 1583814675000,
                    "day": 2
                },
                "headExtraPic": "",
                "aucNumId": 0,
                "displayUserNick": "湟***耋",
                "structuredRateList": [],
                "carServiceLocation": "",
                "userVipPic": "",
                "serviceRateContent": "",
                "memberIcon": "",
                "attributes": "",
                "position": "920-11-4,10;121-11-0,3;",
                "cmsSource": "天猫",
                "tamllSweetLevel": 0,
                "gmtCreateTime": {
                    "date": 12,
                    "hours": 11,
                    "seconds": 56,
                    "month": 2,
                    "timezoneOffset": -480,
                    "year": 120,
                    "minutes": 35,
                    "time": 1583984156000,
                    "day": 4
                },
                "useful": true,
                "displayUserRateLink": ""
            },
            {
                "auctionPicUrl": "",
                "userInfo": "",
                "displayRatePic": "",
                "dsr": 0,
                "displayRateSum": 0,
                "appendComment": null,
                "fromMemory": 0,
                "picsSmall": [],
                "tmallSweetPic": "tmall-grade-t2-18.png",
                "rateDate": "2020-03-12 11:10:07",
                "rateContent": "拍照效果：挺好的，广角功能满意； 运行速度：满足需求（一般小游戏+普通app、拍照等需要） 电池续航：因为是新机现在来看是满意的，用久后电池情况会重点关注",
                "fromMall": true,
                "userIdEncryption": "",
                "sellerId": 2838892713,
                "videoList": [],
                "displayUserLink": "",
                "id": 1077285339600,
                "aliMallSeller": false,
                "reply": "",
                "pics": [],
                "buyCount": 0,
                "userVipLevel": 0,
                "auctionSku": "网络类型:4G全网通;机身颜色:天空之境;套餐类型:官方标配;存储容量:8+256GB",
                "anony": false,
                "displayUserNumId": 0,
                "goldUser": true,
                "attributesMap": null,
                "tradeEndTime": {
                    "date": 12,
                    "hours": 9,
                    "seconds": 44,
                    "month": 2,
                    "timezoneOffset": -480,
                    "year": 120,
                    "minutes": 57,
                    "time": 1583978264000,
                    "day": 4
                },
                "headExtraPic": "",
                "aucNumId": 0,
                "displayUserNick": "w***1",
                "structuredRateList": [],
                "carServiceLocation": "",
                "userVipPic": "",
                "serviceRateContent": "",
                "memberIcon": "",
                "attributes": "",
                "position": "921-12-17,21;90221-11-9,15;920-12-33,38;521-12-65,77;620-12-0,4;20521-12-46,50;40221-12-39,44;620-11-51,64;50221-12-27,32;920-11-5,8;920-11-22,26;",
                "cmsSource": "天猫",
                "tamllSweetLevel": 2,
                "gmtCreateTime": {
                    "date": 12,
                    "hours": 11,
                    "seconds": 7,
                    "month": 2,
                    "timezoneOffset": -480,
                    "year": 120,
                    "minutes": 10,
                    "time": 1583982607000,
                    "day": 4
                },
                "useful": true,
                "displayUserRateLink": ""
            },
            {
                "auctionPicUrl": "",
                "userInfo": "",
                "displayRatePic": "",
                "dsr": 0,
                "displayRateSum": 0,
                "appendComment": null,
                "fromMemory": 0,
                "picsSmall": [],
                "tmallSweetPic": "tmall-grade-t1-18.png",
                "rateDate": "2020-03-12 11:00:47",
                "rateContent": "已经收到，正品，很好用",
                "fromMall": true,
                "userIdEncryption": "",
                "sellerId": 2838892713,
                "videoList": [],
                "displayUserLink": "",
                "id": 1076779705534,
                "aliMallSeller": false,
                "reply": "",
                "pics": [],
                "buyCount": 0,
                "userVipLevel": 0,
                "auctionSku": "网络类型:4G全网通;机身颜色:亮黑色;套餐类型:官方标配;存储容量:8+128GB",
                "anony": false,
                "displayUserNumId": 0,
                "goldUser": false,
                "attributesMap": null,
                "tradeEndTime": {
                    "date": 12,
                    "hours": 11,
                    "seconds": 24,
                    "month": 2,
                    "timezoneOffset": -480,
                    "year": 120,
                    "minutes": 0,
                    "time": 1583982024000,
                    "day": 4
                },
                "headExtraPic": "",
                "aucNumId": 0,
                "displayUserNick": "卢***2",
                "structuredRateList": [],
                "carServiceLocation": "",
                "userVipPic": "",
                "serviceRateContent": "",
                "memberIcon": "",
                "attributes": "",
                "position": "920-11-8,11;1020-11-5,7;",
                "cmsSource": "天猫",
                "tamllSweetLevel": 1,
                "gmtCreateTime": {
                    "date": 12,
                    "hours": 11,
                    "seconds": 47,
                    "month": 2,
                    "timezoneOffset": -480,
                    "year": 120,
                    "minutes": 0,
                    "time": 1583982047000,
                    "day": 4
                },
                "useful": true,
                "displayUserRateLink": ""
            },
            {
                "auctionPicUrl": "",
                "userInfo": "",
                "displayRatePic": "",
                "dsr": 0,
                "displayRateSum": 0,
                "appendComment": null,
                "fromMemory": 0,
                "picsSmall": [],
                "tmallSweetPic": "",
                "rateDate": "2020-03-12 10:49:28",
                "rateContent": "外形看起来舒服，双面玻璃，握起来很有手感，也很大气，手感不错，有份量，音效也还不错，摄像头实拍真实，拍出来的视频也还可以，下了几个 app 运行的还比较顺畅，暂无卡顿，快充功能充电很快，整体来说是个不错的选择！",
                "fromMall": true,
                "userIdEncryption": "",
                "sellerId": 2838892713,
                "videoList": [],
                "displayUserLink": "",
                "id": 1076527316327,
                "aliMallSeller": false,
                "reply": "",
                "pics": [
                    "//img.alicdn.com/bao/uploaded/i1/O1CN01kyzFAl1ava2bJeYNG_!!0-rate.jpg",
                    "//img.alicdn.com/bao/uploaded/i3/O1CN01YtjbJM1ava2jZlqi0_!!0-rate.jpg"
                ],
                "buyCount": 0,
                "userVipLevel": 0,
                "auctionSku": "网络类型:4G全网通;机身颜色:天空之境;套餐类型:官方标配;存储容量:8+128GB",
                "anony": true,
                "displayUserNumId": 0,
                "goldUser": false,
                "attributesMap": null,
                "tradeEndTime": {
                    "date": 12,
                    "hours": 1,
                    "seconds": 29,
                    "month": 2,
                    "timezoneOffset": -480,
                    "year": 120,
                    "minutes": 8,
                    "time": 1583946509000,
                    "day": 4
                },
                "headExtraPic": "",
                "aucNumId": 0,
                "displayUserNick": "t***8",
                "structuredRateList": [],
                "carServiceLocation": "",
                "userVipPic": "",
                "serviceRateContent": "",
                "memberIcon": "",
                "attributes": "",
                "position": "121-11-21,25;721-11-26,30;620-11-93,104;40221-11-42,49;721-12-13,20;80221-11-50,60;10521-11-84,92;921-11-84,92;921-11-70,78;121-11-0,7;30221-11-35,41;",
                "cmsSource": "天猫",
                "tamllSweetLevel": 0,
                "gmtCreateTime": {
                    "date": 12,
                    "hours": 10,
                    "seconds": 28,
                    "month": 2,
                    "timezoneOffset": -480,
                    "year": 120,
                    "minutes": 49,
                    "time": 1583981368000,
                    "day": 4
                },
                "useful": true,
                "displayUserRateLink": ""
            },
            {
                "auctionPicUrl": "",
                "userInfo": "",
                "displayRatePic": "",
                "dsr": 0,
                "displayRateSum": 0,
                "appendComment": null,
                "fromMemory": 0,
                "picsSmall": [],
                "tmallSweetPic": "",
                "rateDate": "2020-03-12 10:00:47",
                "rateContent": "p30珠光贝母太好看！用用再来！",
                "fromMall": true,
                "userIdEncryption": "",
                "sellerId": 2838892713,
                "videoList": [],
                "displayUserLink": "",
                "id": 1076774781084,
                "aliMallSeller": false,
                "reply": "",
                "pics": [],
                "buyCount": 0,
                "userVipLevel": 0,
                "auctionSku": "网络类型:4G全网通;机身颜色:珠光贝母;套餐类型:官方标配;存储容量:8+128GB",
                "anony": false,
                "displayUserNumId": 0,
                "goldUser": false,
                "attributesMap": null,
                "tradeEndTime": {
                    "date": 8,
                    "hours": 12,
                    "seconds": 10,
                    "month": 2,
                    "timezoneOffset": -480,
                    "year": 120,
                    "minutes": 4,
                    "time": 1583640250000,
                    "day": 0
                },
                "headExtraPic": "",
                "aucNumId": 0,
                "displayUserNick": "d***2",
                "structuredRateList": [],
                "carServiceLocation": "",
                "userVipPic": "",
                "serviceRateContent": "",
                "memberIcon": "",
                "attributes": "",
                "position": "111;121-11-0,10;",
                "cmsSource": "天猫",
                "tamllSweetLevel": 0,
                "gmtCreateTime": {
                    "date": 12,
                    "hours": 10,
                    "seconds": 47,
                    "month": 2,
                    "timezoneOffset": -480,
                    "year": 120,
                    "minutes": 0,
                    "time": 1583978447000,
                    "day": 4
                },
                "useful": true,
                "displayUserRateLink": ""
            },
            {
                "auctionPicUrl": "",
                "userInfo": "",
                "displayRatePic": "",
                "dsr": 0,
                "displayRateSum": 0,
                "appendComment": null,
                "fromMemory": 0,
                "picsSmall": [],
                "tmallSweetPic": "",
                "rateDate": "2020-03-12 09:13:31",
                "rateContent": "手机贴膜据说很难贴  希望我的屏幕稳住 像我这种手机很容易掉地上的  不知道会不会碎屏 h",
                "fromMall": true,
                "userIdEncryption": "",
                "sellerId": 2838892713,
                "videoList": [],
                "displayUserLink": "",
                "id": 1076771329057,
                "aliMallSeller": false,
                "reply": "天苍苍，野茫茫，您有疑问我帮忙~关于您的问题，建议您去咱们线下服务中心进行专业的贴膜哦~如您后续使用中存在问题，您可以进线咨询在线客服，我们全力为您解答，愿平安喜乐，忧愁再无打扰~",
                "pics": [],
                "buyCount": 0,
                "userVipLevel": 0,
                "auctionSku": "网络类型:4G全网通;机身颜色:珠光贝母;套餐类型:官方标配;存储容量:8+128GB",
                "anony": false,
                "displayUserNumId": 0,
                "goldUser": false,
                "attributesMap": null,
                "tradeEndTime": {
                    "date": 2,
                    "hours": 11,
                    "seconds": 43,
                    "month": 2,
                    "timezoneOffset": -480,
                    "year": 120,
                    "minutes": 11,
                    "time": 1583118703000,
                    "day": 1
                },
                "headExtraPic": "",
                "aucNumId": 0,
                "displayUserNick": "冷***么",
                "structuredRateList": [],
                "carServiceLocation": "",
                "userVipPic": "",
                "serviceRateContent": "",
                "memberIcon": "",
                "attributes": "",
                "position": "621-12-0,9;620-13-20,33;",
                "cmsSource": "天猫",
                "tamllSweetLevel": 0,
                "gmtCreateTime": {
                    "date": 12,
                    "hours": 9,
                    "seconds": 31,
                    "month": 2,
                    "timezoneOffset": -480,
                    "year": 120,
                    "minutes": 13,
                    "time": 1583975611000,
                    "day": 4
                },
                "useful": true,
                "displayUserRateLink": ""
            }
        ],
        "searchinfo": "",
        "from": "search",
        "paginator": {
            "lastPage": 99,
            "page": 10,
            "items": 45110
        },
        "tags": []
    }
}