{
    "commodityReviews": [
        {
            "bestTag": 0,
            "commodityReviewId": 695821012,
            "content": "拍照无敌，外观很喜欢，在5G普及以前，这个是最好的手机了",
            "publishTime": "2019-12-20 18:40:17",
            "publishTimeStr": "2019-12-20 18:40:17",
            "deviceType": 5,
            "sourceSystem": "android",
            "anonFlag": true,
            "userInfo": {
                "nickName": "1***7",
                "levelId": "161000000130",
                "levelName": "V3",
                "imgUrl": "//image.suning.cn/uimg/cmf/cust_headpic/0000000000_33_60x60.jpg",
                "isVip": false
            },
            "qualityStar": 5,
            "bestFlag": false,
            "shopInfo": {
                "shopId": "0000000000",
                "shopName": "苏宁自营",
                "shopType": "1"
            },
            "picVideoFlag": true,
            "contentLength": 28,
            "picVideInfo": {
                "imgCount": 2,
                "imageInfo": [
                    {
                        "imgSeq": 0,
                        "url": "//image.suning.cn/uimg/ZR/share_order/157683834100556437",
                        "coverFlag": false,
                        "ordershowId": 0
                    },
                    {
                        "imgSeq": 1,
                        "url": "//image.suning.cn/uimg/ZR/share_order/157683834084279258",
                        "coverFlag": false,
                        "ordershowId": 0
                    }
                ]
            },
            "commodityInfo": {
                "commodityCode": "000000010973073813",
                "commodityName": "华为/HUAWEI P30 Pro 天空之境 8GB+256GB 超感光四摄 未来影像 移动联通电信4G全面屏全网通手机",
                "buyCatalogId": "R1901001",
                "charaterId1": "颜色",
                "charaterDesc1": "天空之境",
                "charaterId2": "版本",
                "charaterDesc2": "8GB+256GB"
            },
            "againFlag": false,
            "individualObject": [],
            "labelNames": [],
            "score": 0.0,
            "againReview": {
                "againPicFlag": 0
            },
            "usefulCnt": 0,
            "replyCnt": 0,
            "replyFlag": false,
            "isShowReviewDetail": true,
            "styleId": "",
            "groupId": "30357465",
            "againReviewImgFlag": false,
            "againReviewImgList": [],
            "voiceFlag": false,
            "smallVideoFlag": false,
            "imgCnt": 2,
            "canUploadImg": true,
            "ordinaryContent": "拍照无敌，外观很喜欢，在5G普及以前，这个是最好的手机了",
            "returnCode": "1",
            "returnMsg": ""
        },
        {
            "bestTag": 0,
            "commodityReviewId": 695754322,
            "content": "拍照效果：拍照技术含量一下子好的好的好的",
            "publishTime": "2019-12-20 13:43:35",
            "publishTimeStr": "2019-12-20 13:43:35",
            "deviceType": 5,
            "sourceSystem": "android",
            "anonFlag": true,
            "userInfo": {
                "nickName": "1***5",
                "levelId": "161000000140",
                "levelName": "V4",
                "imgUrl": "//image.suning.cn/uimg/cmf/cust_headpic/0000000000_26_60x60.jpg",
                "isVip": true
            },
            "qualityStar": 5,
            "bestFlag": false,
            "shopInfo": {
                "shopId": "0000000000",
                "shopName": "苏宁自营",
                "shopType": "1"
            },
            "picVideoFlag": true,
            "contentLength": 20,
            "picVideInfo": {
                "imgCount": 3,
                "imageInfo": [
                    {
                        "imgSeq": 0,
                        "url": "//image.suning.cn/uimg/ZR/share_order/157682055812186842",
                        "coverFlag": false
                    },
                    {
                        "imgSeq": 1,
                        "url": "//image.suning.cn/uimg/ZR/share_order/157682055922793479",
                        "coverFlag": false
                    },
                    {
                        "imgSeq": 2,
                        "url": "//image.suning.cn/uimg/ZR/share_order/157682056096811717",
                        "coverFlag": false
                    }
                ]
            },
            "commodityInfo": {
                "commodityCode": "000000010973073813",
                "commodityName": "华为/HUAWEI P30 Pro 天空之境 8GB+256GB 超感光四摄 未来影像 移动联通电信4G全面屏全网通手机",
                "buyCatalogId": "R1901001",
                "charaterId1": "颜色",
                "charaterDesc1": "天空之境",
                "charaterId2": "版本",
                "charaterDesc2": "8GB+256GB"
            },
            "againFlag": false,
            "individualObject": [],
            "labelNames": [],
            "score": 0.0,
            "againReview": {
                "againPicFlag": 0
            },
            "usefulCnt": 0,
            "replyCnt": 0,
            "replyFlag": false,
            "isShowReviewDetail": true,
            "styleId": "",
            "groupId": "30357465",
            "againReviewImgFlag": false,
            "againReviewImgList": [],
            "voiceFlag": false,
            "smallVideoFlag": false,
            "imgCnt": 3,
            "canUploadImg": true,
            "guideLabelDTOList": [
                {
                    "labelId": "328",
                    "labelName": "拍照效果",
                    "content": "拍照技术含量一下子好的好的好的"
                }
            ],
            "ordinaryContent": "",
            "returnCode": "1",
            "returnMsg": ""
        },
        {
            "bestTag": 0,
            "commodityReviewId": 695702840,
            "content": "电池续航：不错<br/>显示效果：色差好",
            "publishTime": "2019-12-20 09:44:03",
            "publishTimeStr": "2019-12-20 09:44:03",
            "deviceType": 5,
            "sourceSystem": "android",
            "anonFlag": false,
            "userInfo": {
                "nickName": "1***0",
                "levelId": "161000000140",
                "levelName": "V4",
                "imgUrl": "//image.suning.cn/uimg/cmf/cust_headpic/0000000000_26_60x60.jpg",
                "isVip": true
            },
            "qualityStar": 5,
            "bestFlag": false,
            "shopInfo": {
                "shopId": "0000000000",
                "shopName": "苏宁自营",
                "shopType": "1"
            },
            "picVideoFlag": false,
            "contentLength": 16,
            "commodityInfo": {
                "commodityCode": "000000010973073813",
                "commodityName": "华为/HUAWEI P30 Pro 天空之境 8GB+256GB 超感光四摄 未来影像 移动联通电信4G全面屏全网通手机",
                "buyCatalogId": "R1901001",
                "charaterId1": "颜色",
                "charaterDesc1": "天空之境",
                "charaterId2": "版本",
                "charaterDesc2": "8GB+256GB"
            },
            "againFlag": false,
            "individualObject": [],
            "labelNames": [],
            "score": 0.0,
            "againReview": {
                "againPicFlag": 0
            },
            "usefulCnt": 0,
            "replyCnt": 0,
            "replyFlag": false,
            "isShowReviewDetail": false,
            "styleId": "",
            "groupId": "30357465",
            "againReviewImgFlag": false,
            "againReviewImgList": [],
            "voiceFlag": false,
            "smallVideoFlag": false,
            "imgCnt": 0,
            "canUploadImg": true,
            "guideLabelDTOList": [
                {
                    "labelId": "331",
                    "labelName": "电池续航",
                    "content": "不错"
                },
                {
                    "labelId": "325",
                    "labelName": "显示效果",
                    "content": "色差好"
                }
            ],
            "ordinaryContent": "",
            "returnCode": "1",
            "returnMsg": ""
        },
        {
            "bestTag": 0,
            "commodityReviewId": 695668357,
            "content": "此用户没有填写评价内容",
            "publishTime": "2019-12-19 23:56:32",
            "publishTimeStr": "2019-12-19 23:56:32",
            "deviceType": 5,
            "sourceSystem": "android",
            "anonFlag": false,
            "userInfo": {
                "nickName": "z***m",
                "levelId": "161000000140",
                "levelName": "V4",
                "imgUrl": "//image.suning.cn/uimg/cmf/cust_headpic/0000000000_26_60x60.jpg",
                "isVip": false
            },
            "qualityStar": 5,
            "bestFlag": false,
            "shopInfo": {
                "shopId": "0000000000",
                "shopName": "苏宁自营",
                "shopType": "1"
            },
            "picVideoFlag": false,
            "contentLength": 11,
            "commodityInfo": {
                "commodityCode": "000000010973073813",
                "commodityName": "华为/HUAWEI P30 Pro 天空之境 8GB+256GB 超感光四摄 未来影像 移动联通电信4G全面屏全网通手机",
                "buyCatalogId": "R1901001",
                "charaterId1": "颜色",
                "charaterDesc1": "天空之境",
                "charaterId2": "版本",
                "charaterDesc2": "8GB+256GB"
            },
            "againFlag": false,
            "individualObject": [],
            "labelNames": [],
            "score": 0.0,
            "againReview": {
                "againPicFlag": 0
            },
            "usefulCnt": 0,
            "replyCnt": 0,
            "replyFlag": false,
            "isShowReviewDetail": false,
            "styleId": "",
            "groupId": "30357465",
            "againReviewImgFlag": false,
            "againReviewImgList": [],
            "voiceFlag": false,
            "smallVideoFlag": false,
            "imgCnt": 0,
            "canUploadImg": true,
            "ordinaryContent": "",
            "returnCode": "1",
            "returnMsg": ""
        },
        {
            "bestTag": 0,
            "commodityReviewId": 695625456,
            "content": "电池续航：续航能力很棒，满意<br/>拍照效果：拍照清晰，效果不错，满意<br/>显示效果：屏幕清晰，手感很好，满意，外观惊艳，太喜欢了，手感非常好。主要是价钱比***某宝便宜，捡到宝啦",
            "publishTime": "2019-12-19 19:55:11",
            "publishTimeStr": "2019-12-19 19:55:11",
            "deviceType": 5,
            "sourceSystem": "android",
            "anonFlag": false,
            "userInfo": {
                "nickName": "1***1",
                "levelId": "161000000130",
                "levelName": "V3",
                "imgUrl": "//image.suning.cn/uimg/cmf/cust_headpic/0000000000_33_60x60.jpg",
                "isVip": false
            },
            "qualityStar": 5,
            "bestFlag": false,
            "shopInfo": {
                "shopId": "0000000000",
                "shopName": "苏宁自营",
                "shopType": "1"
            },
            "picVideoFlag": true,
            "contentLength": 85,
            "picVideInfo": {
                "imgCount": 4,
                "imageInfo": [
                    {
                        "imgSeq": 0,
                        "url": "//image.suning.cn/uimg/ZR/share_order/157675634176595636",
                        "coverFlag": false
                    },
                    {
                        "imgSeq": 1,
                        "url": "//image.suning.cn/uimg/ZR/share_order/157675634185443058",
                        "coverFlag": false
                    },
                    {
                        "imgSeq": 2,
                        "url": "//image.suning.cn/uimg/ZR/share_order/157675634220252514",
                        "coverFlag": false
                    },
                    {
                        "imgSeq": 3,
                        "url": "//image.suning.cn/uimg/ZR/share_order/157675634190115411",
                        "coverFlag": false
                    }
                ]
            },
            "commodityInfo": {
                "commodityCode": "000000010973073813",
                "commodityName": "华为/HUAWEI P30 Pro 天空之境 8GB+256GB 超感光四摄 未来影像 移动联通电信4G全面屏全网通手机",
                "buyCatalogId": "R1901001",
                "charaterId1": "颜色",
                "charaterDesc1": "天空之境",
                "charaterId2": "版本",
                "charaterDesc2": "8GB+256GB"
            },
            "againFlag": false,
            "individualObject": [],
            "labelNames": [
                {
                    "labelName": "拍照效果好"
                },
                {
                    "labelName": "外观漂亮"
                },
                {
                    "labelName": "屏幕清晰"
                }
            ],
            "score": 0.0,
            "againReview": {
                "againPicFlag": 0
            },
            "usefulCnt": 0,
            "replyCnt": 0,
            "replyFlag": false,
            "isShowReviewDetail": true,
            "styleId": "",
            "groupId": "30357465",
            "againReviewImgFlag": false,
            "againReviewImgList": [],
            "voiceFlag": false,
            "smallVideoFlag": false,
            "imgCnt": 4,
            "canUploadImg": true,
            "guideLabelDTOList": [
                {
                    "labelId": "331",
                    "labelName": "电池续航",
                    "content": "续航能力很棒，满意"
                },
                {
                    "labelId": "328",
                    "labelName": "拍照效果",
                    "content": "拍照清晰，效果不错，满意"
                },
                {
                    "labelId": "325",
                    "labelName": "显示效果",
                    "content": "屏幕清晰，手感很好，满意，外观惊艳，太喜欢了，手感非常好。\n主要是价钱比***某宝便宜，捡到宝啦"
                }
            ],
            "ordinaryContent": "",
            "returnCode": "1",
            "returnMsg": ""
        },
        {
            "bestTag": 0,
            "commodityReviewId": 695484002,
            "content": "先说价格，比较了***和苏宁，苏宁价格便宜很多，再说手机，手机外观比较炫但是个人感觉没有图片那么蓝，有色差，手机流畅性很不错。再说送货，比起普通商品，手机送货太慢了，双12买的，14号下午才收到",
            "publishTime": "2019-12-19 09:58:50",
            "publishTimeStr": "2019-12-19 09:58:50",
            "deviceType": 5,
            "sourceSystem": "android",
            "anonFlag": false,
            "userInfo": {
                "nickName": "1***3",
                "levelId": "161000000140",
                "levelName": "V4",
                "imgUrl": "//image.suning.cn/uimg/cmf/cust_headpic/0000000000_24_60x60.jpg",
                "isVip": true
            },
            "qualityStar": 5,
            "bestFlag": false,
            "shopInfo": {
                "shopId": "0000000000",
                "shopName": "苏宁自营",
                "shopType": "1"
            },
            "picVideoFlag": true,
            "contentLength": 97,
            "picVideInfo": {
                "imgCount": 3,
                "imageInfo": [
                    {
                        "imgSeq": 0,
                        "url": "//image.suning.cn/uimg/ZR/share_order/157672062129375337",
                        "coverFlag": false
                    },
                    {
                        "imgSeq": 1,
                        "url": "//image.suning.cn/uimg/ZR/share_order/157672061614327774",
                        "coverFlag": false
                    },
                    {
                        "imgSeq": 2,
                        "url": "//image.suning.cn/uimg/ZR/share_order/157672061688375138",
                        "coverFlag": false
                    }
                ]
            },
            "commodityInfo": {
                "commodityCode": "000000010973073813",
                "commodityName": "华为/HUAWEI P30 Pro 天空之境 8GB+256GB 超感光四摄 未来影像 移动联通电信4G全面屏全网通手机",
                "buyCatalogId": "R1901001",
                "charaterId1": "颜色",
                "charaterDesc1": "天空之境",
                "charaterId2": "版本",
                "charaterDesc2": "8GB+256GB"
            },
            "againFlag": false,
            "individualObject": [],
            "labelNames": [
                {
                    "labelName": "外观漂亮"
                }
            ],
            "score": 0.0,
            "againReview": {
                "againPicFlag": 0
            },
            "usefulCnt": 0,
            "replyCnt": 0,
            "replyFlag": false,
            "isShowReviewDetail": true,
            "styleId": "",
            "groupId": "30357465",
            "againReviewImgFlag": false,
            "againReviewImgList": [],
            "voiceFlag": false,
            "smallVideoFlag": false,
            "imgCnt": 3,
            "canUploadImg": true,
            "ordinaryContent": "先说价格，比较了***和苏宁，苏宁价格便宜很多，再说手机，手机外观比较炫但是个人感觉没有图片那么蓝，有色差，手机流畅性很不错。再说送货，比起普通商品，手机送货太慢了，双12买的，14号下午才收到",
            "returnCode": "1",
            "returnMsg": ""
        },
        {
            "bestTag": 0,
            "commodityReviewId": 695194184,
            "content": "手机你想象的小，外观漂亮，速度很快",
            "publishTime": "2019-12-18 07:07:10",
            "publishTimeStr": "2019-12-18 07:07:10",
            "deviceType": 6,
            "sourceSystem": "ios",
            "anonFlag": true,
            "userInfo": {
                "nickName": "c***m",
                "levelId": "161000000130",
                "levelName": "V3",
                "imgUrl": "//image.suning.cn/uimg/cmf/cust_headpic/0000000000_33_60x60.jpg",
                "isVip": false
            },
            "qualityStar": 5,
            "bestFlag": false,
            "shopInfo": {
                "shopId": "0000000000",
                "shopName": "苏宁自营",
                "shopType": "1"
            },
            "picVideoFlag": false,
            "contentLength": 17,
            "commodityInfo": {
                "commodityCode": "000000010973073813",
                "commodityName": "华为/HUAWEI P30 Pro 天空之境 8GB+256GB 超感光四摄 未来影像 移动联通电信4G全面屏全网通手机",
                "buyCatalogId": "R1901001",
                "charaterId1": "版本",
                "charaterDesc1": "8GB+256GB",
                "charaterId2": "颜色",
                "charaterDesc2": "天空之境"
            },
            "againFlag": false,
            "individualObject": [],
            "labelNames": [
                {
                    "labelName": "外观漂亮"
                }
            ],
            "score": 0.0,
            "againReview": {
                "againPicFlag": 0
            },
            "usefulCnt": 0,
            "replyCnt": 0,
            "replyFlag": false,
            "isShowReviewDetail": false,
            "styleId": "",
            "groupId": "30357465",
            "againReviewImgFlag": false,
            "againReviewImgList": [],
            "voiceFlag": false,
            "smallVideoFlag": false,
            "imgCnt": 0,
            "canUploadImg": true,
            "ordinaryContent": "",
            "returnCode": "1",
            "returnMsg": ""
        },
        {
            "bestTag": 0,
            "commodityReviewId": 695177973,
            "content": "此用户没有填写评价内容",
            "publishTime": "2019-12-18 00:17:32",
            "publishTimeStr": "2019-12-18 00:17:32",
            "deviceType": 5,
            "sourceSystem": "android",
            "anonFlag": false,
            "userInfo": {
                "nickName": "1***2",
                "levelId": "161000000120",
                "levelName": "V2",
                "imgUrl": "//image.suning.cn/uimg/cmf/cust_headpic/0000000000_33_60x60.jpg",
                "isVip": false
            },
            "qualityStar": 4,
            "bestFlag": false,
            "shopInfo": {
                "shopId": "0000000000",
                "shopName": "苏宁自营",
                "shopType": "1"
            },
            "picVideoFlag": false,
            "contentLength": 11,
            "commodityInfo": {
                "commodityCode": "000000010973073813",
                "commodityName": "华为/HUAWEI P30 Pro 天空之境 8GB+256GB 超感光四摄 未来影像 移动联通电信4G全面屏全网通手机",
                "buyCatalogId": "R1901001",
                "charaterId1": "版本",
                "charaterDesc1": "8GB+256GB",
                "charaterId2": "颜色",
                "charaterDesc2": "天空之境"
            },
            "againFlag": false,
            "individualObject": [],
            "labelNames": [],
            "score": 0.0,
            "againReview": {
                "againPicFlag": 0
            },
            "usefulCnt": 0,
            "replyCnt": 0,
            "replyFlag": false,
            "isShowReviewDetail": false,
            "styleId": "",
            "groupId": "30357465",
            "againReviewImgFlag": false,
            "againReviewImgList": [],
            "voiceFlag": false,
            "smallVideoFlag": false,
            "imgCnt": 0,
            "canUploadImg": true,
            "ordinaryContent": "",
            "returnCode": "1",
            "returnMsg": ""
        },
        {
            "bestTag": 0,
            "commodityReviewId": 695111818,
            "content": "拍照效果简直太好了，大片既视感，值了",
            "publishTime": "2019-12-17 20:06:45",
            "publishTimeStr": "2019-12-17 20:06:45",
            "deviceType": 5,
            "sourceSystem": "android",
            "anonFlag": true,
            "userInfo": {
                "nickName": "1***2",
                "levelId": "161000000110",
                "levelName": "V1",
                "imgUrl": "//image.suning.cn/uimg/cmf/cust_headpic/0000000000_33_60x60.jpg",
                "isVip": false
            },
            "qualityStar": 5,
            "bestFlag": false,
            "shopInfo": {
                "shopId": "0000000000",
                "shopName": "苏宁自营",
                "shopType": "1"
            },
            "picVideoFlag": true,
            "contentLength": 18,
            "picVideInfo": {
                "imgCount": 2,
                "imageInfo": [
                    {
                        "imgSeq": 0,
                        "url": "//image.suning.cn/uimg/ZR/share_order/157658432898121789",
                        "coverFlag": false,
                        "ordershowId": 0
                    },
                    {
                        "imgSeq": 1,
                        "url": "//image.suning.cn/uimg/ZR/share_order/157658432969272598",
                        "coverFlag": false,
                        "ordershowId": 0
                    }
                ]
            },
            "commodityInfo": {
                "commodityCode": "000000010973073813",
                "commodityName": "华为/HUAWEI P30 Pro 天空之境 8GB+256GB 超感光四摄 未来影像 移动联通电信4G全面屏全网通手机",
                "buyCatalogId": "R1901001",
                "charaterId1": "颜色",
                "charaterDesc1": "天空之境",
                "charaterId2": "版本",
                "charaterDesc2": "8GB+256GB"
            },
            "againFlag": false,
            "individualObject": [],
            "labelNames": [],
            "score": 0.0,
            "againReview": {
                "againPicFlag": 0
            },
            "usefulCnt": 0,
            "replyCnt": 0,
            "replyFlag": false,
            "isShowReviewDetail": true,
            "styleId": "",
            "groupId": "30357465",
            "againReviewImgFlag": false,
            "againReviewImgList": [],
            "voiceFlag": false,
            "smallVideoFlag": false,
            "imgCnt": 2,
            "canUploadImg": true,
            "ordinaryContent": "拍照效果简直太好了，大片既视感，值了",
            "returnCode": "1",
            "returnMsg": ""
        },
        {
            "bestTag": 0,
            "commodityReviewId": 694992460,
            "content": "电池续航：超强的，到货有60%电量，用了一天。<br/>拍照效果：这个手机的拍照效果就不用多提了吧，***！<br/>显示效果：屏幕色彩非常棒，曲面屏新的体验！<br/>值得入手！",
            "publishTime": "2019-12-17 14:10:44",
            "publishTimeStr": "2019-12-17 14:10:44",
            "deviceType": 5,
            "sourceSystem": "android",
            "anonFlag": false,
            "userInfo": {
                "nickName": "3***m",
                "levelId": "161000000120",
                "levelName": "V2",
                "imgUrl": "//image.suning.cn/uimg/cmf/cust_headpic/0000000000_24_60x60.jpg",
                "isVip": true
            },
            "qualityStar": 5,
            "bestFlag": false,
            "shopInfo": {
                "shopId": "0000000000",
                "shopName": "苏宁自营",
                "shopType": "1"
            },
            "picVideoFlag": true,
            "contentLength": 78,
            "picVideInfo": {
                "imgCount": 3,
                "imageInfo": [
                    {
                        "imgSeq": 0,
                        "url": "//image.suning.cn/uimg/ZR/share_order/157656295335953775",
                        "coverFlag": false
                    },
                    {
                        "imgSeq": 1,
                        "url": "//image.suning.cn/uimg/ZR/share_order/157656295367199692",
                        "coverFlag": false
                    },
                    {
                        "imgSeq": 2,
                        "url": "//image.suning.cn/uimg/ZR/share_order/157656295339262448",
                        "coverFlag": false
                    }
                ]
            },
            "commodityInfo": {
                "commodityCode": "000000010973073813",
                "commodityName": "华为/HUAWEI P30 Pro 天空之境 8GB+256GB 超感光四摄 未来影像 移动联通电信4G全面屏全网通手机",
                "buyCatalogId": "R1901001",
                "charaterId1": "颜色",
                "charaterDesc1": "天空之境",
                "charaterId2": "版本",
                "charaterDesc2": "8GB+256GB"
            },
            "againFlag": false,
            "individualObject": [],
            "labelNames": [],
            "score": 0.0,
            "againReview": {
                "againPicFlag": 0
            },
            "usefulCnt": 0,
            "replyCnt": 0,
            "replyFlag": false,
            "isShowReviewDetail": true,
            "styleId": "",
            "groupId": "30357465",
            "againReviewImgFlag": false,
            "againReviewImgList": [],
            "voiceFlag": false,
            "smallVideoFlag": false,
            "imgCnt": 3,
            "canUploadImg": true,
            "guideLabelDTOList": [
                {
                    "labelId": "331",
                    "labelName": "电池续航",
                    "content": "超强的，到货有60%电量，用了一天。"
                },
                {
                    "labelId": "328",
                    "labelName": "拍照效果",
                    "content": "这个手机的拍照效果就不用多提了吧，***！"
                },
                {
                    "labelId": "325",
                    "labelName": "显示效果",
                    "content": "屏幕色彩非常棒，曲面屏新的体验！"
                }
            ],
            "ordinaryContent": "值得入手！",
            "returnCode": "1",
            "returnMsg": ""
        }
    ],
    "returnCode": "1",
    "returnMsg": "成功取得评价列表",
    "reCloudDrill": 0
}